verilog/adder_struct.v
// carry look ahead adder
module adder (A, B, Cin, S, P, G, Cout, OVF);

	////////
	// IO //
	////////
  input  [31:0]  A, B;
  input          Cin;
  output [31:0]	 S, P, G;
  output Cout, OVF;

	////////////////////
	// Internal Nodes //
	////////////////////
	reg    [31:0]  carrychain;
  
	// P, G
	assign G = A & B; // carry generate
  assign P = A ^ B; // carry propagate
  
	// Carry Chain
  always @(*)
    begin : carry_generation
      integer i;
      carrychain[0] = G[0] + (P[0] & Cin);
      for(i = 1; i <= 31; i = i + 1)
        begin
          carrychain[i] = G[i] + (P[i] & carrychain[i-1]);
        end
    end

	/* should redo this so we don't get a ripple carry adder
	// 8 4-bit CLAs that interface directly with the bits
	CLA cla_0 ();
	CLA cla_0 ();
	CLA cla_0 ();
	CLA cla_0 ();
	CLA cla_0 ();
	CLA cla_0 ();
	CLA cla_0 ();
	CLA cla_0 ();
		
	// 2 MS 4-bit CLAs that interface with the lower level CLAs
	CLA cla_0 ();
	CLA cla_0 ();
	*/
	
	// Sum
  wire [32:0] shiftedcarry;

	assign shiftedcarry = {carrychain,Cin};
  assign S = P ^ shiftedcarry[31:0];    // summation
  
	// Carry Out
	assign Cout = shiftedcarry[32];
	
	// Overflow
	assign OVF = shiftedcarry[32] ^ shiftedcarry[31];

endmodule

/* not currently used
// Carry Look-Ahead Unit
module CLA (P, G, C, Cout, Pin, Gin, Cin);

	// I/O
	output	[3:0] C;
	output				Cout, P, G;
	input		[3:0] Pin, Gin;
	input					Cin;
	
	assign C[0] = Cin;
	assign C[1] = Gin[0] + (Pin[0] & Cin);
	assign C[2] = Gin[1] + (Pin[1] & Gin[0]) + (Pin[1] & Pin[0] & Cin);
	assign C[3] = Gin[2] + (Pin[2] & Gin[1]) + (Pin[2] & Pin[1] & Gin[0]) + (Pin[2] & Pin[1] & Pin[0] & Cin);
	assign Cout = Gin[3] + (Pin[3] & Gin[2]) + (Pin[3] & Pin[2] & Gin[1]) + (Pin[3] & Pin[2] & Pin[1] & Gin[0]) + (Pin[3] & Pin[2] & Pin[1] & Pin[0] & Cin);
	
	assign P = &Pin;
	assign G = Gin[3] + Pin[3] & Gin[2] + Pin[3] & Pin[2] & Gin[1] + Pin[3] & Pin[2] & Pin[1] & Gin[0];
	
endmodule
*/

verilog/Alu_struct_bu.v
`timescale 1ns / 10 ps
`include "adder_struct.v"

module Alu( Z, A, B, DI, DO, CI, INST, FLAGS, FirstCyc );
input [31:0] A;
input [31:0] B;
input [31:0] DI;
input [3:0] INST;
input CI;
input FirstCyc;
output [31:0] Z;
output [31:0] DO;
output [3:0] FLAGS;
wire  dpa_zero, dpa_one;
wire [3:0] Z_Inst_Z1_, Z_Inst_, Z_BInst_X1_, Z_BInst_;
wire [31:0] Z_AS_, Z_BS_;
wire  Z_passA_, Z_BINVERT__4_, Z_BINVERT_, Z_BCARRY__5_, Z_BCARRY__6_,
     Z_BCARRY_, Z_AS0_, const_1_1_, Z_AS1_, const_2_1_, Z_AS2_, Z_AS3_;
reg [1:0] Z_ASIGN__8_;
wire  const_3_0_;
reg  Z_ASIGN_;
wire  const_4_0_;
reg [31:0] Z_BIN_;
wire [31:0] Z_BI1_, Z_AIN_, Z_AI_;
wire  Z_CarryIn__9_, Z_CarryIn__10_, Z_CarryIn__11_;
reg  Z_CarryIn_;
wire [2:0] const_5_6_;
wire  const_6_1_, Z_DIVIDE_, Z_BI__14_;
wire [31:0] Z_BI_Z1_, Z_BI__13_;
wire  Z_BI__15_;
reg [31:0] Z_BI_;
wire [32:0] Z_SUM_, Z_Z0_, Z_Z1_, Z_Z2_, Z_Z3_, Z_Z4_, Z_Z5_, Z_Z6_, Z_Z7_,
     Z_AdderOutN_;
wire [31:0] Z_BA_X1_, Z_BA_, Z_BB_X1_, Z_BB_;
wire [32:0] Z_Z8_, Z_Z9_, Z_Z10_, Z_Z11_, Z_Z12_, Z_Z13_;
wire  const_7_0_;
wire [32:0] Z_Z14_;
wire  const_8_1_;
wire [32:0] Z_Z15_;
reg [31:0] Z_ZB_;
wire [31:0] Z_ZC__16_;
reg [31:0] Z_ZC_;
wire [31:0] Z_1_;
wire  Z_C_, Z_OVF_, Z_CarryF_, Z_ZeroF__17_, Z_ZeroF_, const_9_0_;
wire [3:0] FLAGS_Z1_, FLAGS_3_;
wire [31:0] DO_Z1_, DO_2_;
assign dpa_zero= 1024'h0;
assign dpa_one= 1024'h1;
assign const_1_1_= 1024'h1;
assign const_2_1_= 1024'h1;
assign const_3_0_= 1024'h0;
assign const_4_0_= 1024'h0;
assign const_5_6_= 1024'h6;
assign const_6_1_= 1024'h1;
assign const_7_0_= 1024'h0;
assign const_8_1_= 1024'h1;
assign const_9_0_= 1024'h0;

assign Z_Inst_Z1_={ INST[3],INST[2],INST[1],INST[0]};

assign Z_Inst_= (Z_Inst_Z1_[3:0]);

assign Z_BInst_X1_ = Z_Inst_[3:0];

assign Z_BInst_ = Z_BInst_X1_[3:0];

assign Z_AS_= (A[31:0]);

assign Z_BS_= (B[31:0]);

assign Z_passA_= (Z_Inst_[2]&Z_Inst_[1]&Z_Inst_[0]);

assign Z_BINVERT__4_= (Z_Inst_[2]&~Z_Inst_[1]);

assign Z_BINVERT_= (Z_Inst_[0]&~Z_BINVERT__4_);

assign Z_BCARRY__5_= (Z_Inst_[0]&Z_Inst_[1]);

assign Z_BCARRY__6_= (~Z_Inst_[0]&~Z_Inst_[1]&~Z_Inst_[2]);

assign Z_BCARRY_= (Z_BCARRY__5_|Z_BCARRY__6_);

assign Z_AS0_= (Z_AS_[31]);

assign Z_AS1_= (const_1_1_);

assign Z_AS2_= (A[31]-B[31]-const_2_1_+1 == (2'b0<<0));

assign Z_AS3_= (Z_AS2_);
always @ (Z_Inst_[1:0]  or Z_AS2_ or Z_AS1_ or Z_AS0_) begin
	case (Z_Inst_[1:0])
		2'd2: Z_ASIGN__8_ = (Z_AS2_);
		2'd1: Z_ASIGN__8_ = (Z_AS1_);
		2'd0: Z_ASIGN__8_ = (Z_AS0_);
		default: Z_ASIGN__8_ = 2'bx;
	endcase
end
always @ (Z_BInst_[2]  or Z_ASIGN__8_ or const_3_0_) begin
	case (Z_BInst_[2])
		1'd1: Z_ASIGN_ = ~(Z_ASIGN__8_[1:0]);
		1'd0: Z_ASIGN_ = ~(const_3_0_);
		default: Z_ASIGN_ = 1'bx;
	endcase
end
always @ (Z_BInst_[1]  or Z_BS_ or const_4_0_) begin
	case (Z_BInst_[1])
		1'd1: Z_BIN_ = ~(Z_BS_[31:0]);
		1'd0: Z_BIN_ = ~(const_4_0_);
		default: Z_BIN_ = 32'bx;
	endcase
end

assign Z_BI1_= (Z_BIN_[31:0]^(-Z_BINVERT_));

assign Z_AIN_= (Z_AS_[31:0]^(-Z_ASIGN_));

assign Z_AI_= (~Z_AIN_[31:0]&~(-Z_passA_));

assign Z_CarryIn__9_= ((-Z_BCARRY_)|~(-Z_ASIGN_));

assign Z_CarryIn__10_= (~(-Z_CarryIn__9_));

// not sure if it's necessary to have CI
// be an input to this module
// ALU should be able to determine
// the value of CI based on the instruction
assign Z_CarryIn__11_= (~CI);
always @ (FirstCyc  or Z_CarryIn__10_ or Z_CarryIn__11_) begin
	case (FirstCyc)
		1'd1: Z_CarryIn_ = ~((-Z_CarryIn__10_));
		1'd0: Z_CarryIn_ = ~(Z_CarryIn__11_);
		default: Z_CarryIn_ = 1'bx;
	endcase
end

assign Z_DIVIDE_= (Z_Inst_[3:0]-const_5_6_[2:0]-const_6_1_+1 == (5'b0<<0));

assign Z_BI__14_= (~DI[31]);

assign Z_BI_Z1_={ Z_BI1_[30:0],Z_BI__14_};

assign Z_BI__13_= (Z_BI_Z1_[31:0]);

assign Z_BI__15_= (~Z_DIVIDE_);
always @ (Z_BI__15_  or Z_BI1_ or Z_BI__13_) begin
	case (Z_BI__15_)
		1'd1: Z_BI_ = ~(Z_BI1_[31:0]);
		1'd0: Z_BI_ = ~(Z_BI__13_[31:0]);
		default: Z_BI_ = 32'bx;
	endcase
end


//adder//
//assign Z_SUM_= (Z_BI_[31:0]+Z_AI_[31:0]+Z_CarryIn_);
adder a1(Z_AI_,Z_BI_,Z_CarryIn_,Z_SUM_[31:0],Z_SUM_[32]);


/*assign Z_Z0_= (Z_SUM_[32:0]);

assign Z_Z1_= (Z_Z0_[32:0]);

assign Z_Z2_= (Z_Z0_[32:0]);

assign Z_Z3_= (Z_Z0_[32:0]);

assign Z_Z4_= (Z_Z0_[32:0]);

assign Z_Z5_= (Z_Z0_[32:0]);

assign Z_Z6_= (Z_Z0_[32:0]);

assign Z_Z7_= (Z_Z0_[32:0]);
*/

//assign Z_AdderOutN_= (~Z_Z0_[32:0]);
assign Z_AdderOutN_ = (~Z_SUM_[32:0]);

assign Z_BA_X1_ = Z_AS_[31:0];

assign Z_BA_ = Z_BA_X1_[31:0];

assign Z_BB_X1_ = Z_BS_[31:0];

assign Z_BB_ = Z_BB_X1_[31:0];

assign Z_Z8_= (Z_BA_[31:0]&Z_BB_[31:0]);

assign Z_Z9_= (Z_BA_[31:0]|Z_BB_[31:0]);

assign Z_Z10_= (Z_BA_[31:0]^Z_BB_[31:0]);

assign Z_Z11_= (~Z_BB_[31:0]);

assign Z_Z12_= (Z_BA_[31:0]);

assign Z_Z13_= (~Z_BA_[31:0]);

assign Z_Z14_= (const_7_0_);

assign Z_Z15_= (const_8_1_);
always @ (Z_BInst_[2:0]  or Z_Z15_ or Z_Z14_ or Z_Z13_ or Z_Z12_ or Z_Z11_
     or Z_Z10_ or Z_Z9_ or Z_Z8_) begin
	case (Z_BInst_[2:0])
		3'd7: Z_ZB_ = (Z_Z15_[32:0]);
		3'd6: Z_ZB_ = (Z_Z14_[32:0]);
		3'd5: Z_ZB_ = (Z_Z13_[32:0]);
		3'd4: Z_ZB_ = (Z_Z12_[32:0]);
		3'd3: Z_ZB_ = (Z_Z11_[32:0]);
		3'd2: Z_ZB_ = (Z_Z10_[32:0]);
		3'd1: Z_ZB_ = (Z_Z9_[32:0]);
		3'd0: Z_ZB_ = (Z_Z8_[32:0]);
		default: Z_ZB_ = 32'bx;
	endcase
end

assign Z_ZC__16_= (~Z_ZB_[31:0]);
always @ (Z_BInst_[3]  or Z_ZC__16_ or Z_AdderOutN_) begin
	case (Z_BInst_[3])
		1'd1: Z_ZC_ = ~(Z_ZC__16_[31:0]);
		1'd0: Z_ZC_ = ~(Z_AdderOutN_[32:0]);
		default: Z_ZC_ = 32'bx;
	endcase
end

assign Z_1_= (Z_ZC_[31:0]);

assign Z_C_= (~Z_AdderOutN_[32]);

assign Z_OVF_= (Z_AI_[31]^Z_BI_[31]^Z_AdderOutN_[32]^Z_AdderOutN_[31]);

assign Z_CarryF_= (Z_C_);

assign Z_ZeroF__17_= (Z_1_[0]|Z_1_[1]|Z_1_[2]|Z_1_[3]|Z_1_[4]|Z_1_[5]|Z_1_[6]
    |Z_1_[7]|Z_1_[8]|Z_1_[9]|Z_1_[10]|Z_1_[11]|Z_1_[12]|Z_1_[13]|Z_1_[14]
    |Z_1_[15]|Z_1_[16]|Z_1_[17]|Z_1_[18]|Z_1_[19]|Z_1_[20]|Z_1_[21]|Z_1_[22]
    |Z_1_[23]|Z_1_[24]|Z_1_[25]|Z_1_[26]|Z_1_[27]|Z_1_[28]|Z_1_[29]|Z_1_[30]
    |Z_1_[31]);

assign Z_ZeroF_= (~Z_ZeroF__17_);

assign FLAGS_Z1_={ const_9_0_,Z_ZeroF_,Z_CarryF_,Z_OVF_};

assign FLAGS_3_= (FLAGS_Z1_[3:0]);

assign DO_Z1_={ DI[30:0],Z_C_};

assign DO_2_= (DO_Z1_[31:0]);

assign Z = Z_1_[31:0];

assign DO = DO_2_[31:0];

assign FLAGS = FLAGS_3_[3:0];

/*User Defined Aliases */
endmodule

pt_scripts/random.vcd
$date
        Mon Mar 20 11:53:20 2006
$end

$version
        Synopsys VCS version 7.2.1
$end

$timescale
        1ns
$end

$scope module Alu $end
$var wire 32 A A [31:0] $end
$var wire 32 B B [31:0] $end
$var wire 1 C CI $end
$var wire 32 D DI [31:0] $end
$var wire 1 F FirstCyc $end
$var wire 4 I INST [3:0] $end

$upscope $end

$enddefinitions $end

#0
$dumpvars
b0000000000000000000000000000000 A
b0000000000000000000000000000000 B
b0000000000000000000000000000000 D
b0010 I
0C
0F
$end


#2
b0000000000000000000000000000000 A
b0000000000000000000000000000000 B

#4
b0000000000000000000000000000001 A
b0000000000000000000000000000000 B

#6
b1111111111111111111111111111111 B
b0000000000000000000000000000001 A

#8
b1111111111111111111111111111111 B
b0000000000000000000000000000000 A

#10
b0000000000000000000000000000001 B
b0000000000000000000000000000000 A

#12
b0000000000000000000000000000001 B
b0000000000000000000000000000001 A

#14
b00011001110000011100001100111101 A
b11111111111111111111111111111111 B

#16
b00011001110000011100001100111101 A
b00000000000000000000000000000000 B

#18
b10100110001111100011110011000010 A
b00000100100010001000011100110111 B

#20
b01011001110000011100001100111101 A
b00000100100010001000011100110111 B

#22
b01011001110000011100001100111101 A
b11111111011101110110100001111100 B

#24
b10100110001111100011110011000010 A
b10111101100011110110110001011101 B

#26
b01011001110000011100001100111101 A
b01000010011100001001001110100010 B

#28
b10100111000011100011001011000010 A
b00111001000011100110110101011101 B

#30
b10100111010010100011001011101010 A
b11000110111100001001011010100010 B

#32
b10001000010101010100110100001101 A
b11000110111100001001011011100010 B

#34
b10001000010101010100110100001101 A
b00111001000011110110100100011101 B

#36
b10001000010101010100110100001101 A
b11000110101100001001011011100000 B

#38
b01110111101000101011001011110010 A
b01000110110100101001011001110001 B

#40
b01010111001000011011001111110010 A
b01000110110100101001011001110001 B

#42
b00001100111111100000110010011101 A
b01000110110100101001011001110001 B

#44
b00001100111111100000110010011101 A
b01000110110110101001011001110001 B

#46
b10110011100010011111101111100010 A
b10111001001001010110100110001110 B

#48
b01001110011101100000010000011101 A
b10111101001001010110100110101110 B

#50
b10100011100010011111101111110010 A
b10111100001001110110100111101110 B

#52
b10100011100010011111101111110010 A
b01000011110110001001011010010001 B

#54
b01011100011101100000010000001101 A
b00111101000111000011100100001011 B

#56
b10100011100010011111101111110010 A
b11000010111000111100011011110100 B

#58
b10101110011010111100111111000001 A
b01111011101101111110011010110011 B

#60
b11100110110011110110111111000001 A
b10000100010010000001100101001100 B

#62
b11100110110011110110111111000001 A
b10101000100111000100001010011100 B

#64
b11100110110011110110111111000001 A
b01010111011000111011110101100011 B

#66
b11111111011011110110101111010011 A
b10101000100111000100001010011100 B

#68
b00000000100100001001010000101100 A
b11001110101100111011100000000011 B

#70
b00000000100101001101010000101100 A
b00110001010011000100011111111100 B

#72
b00000000100101001101010000100100 A
b11101011001011010111011111011111 B

#74
b11111111011010110010101111011011 A
b00010100110100101000100000100000 B

#76
b11111111011010110010101111011011 A
b11011111111011100010101100101010 B

#78
b11011110101001000110100110000011 A
b10010111111111100010101000101010 B

#80
b11011110101001000110100110000011 A
b10010111111111100010101000101010 B

#82
b00100000010110111001011001111100 A
b00001011101110101011001100101110 B

#84
b00100000010110111001011001111100 A
b00001011101110101011001100101110 B

#86
b10000011111011111101001001110000 A
b10101100110001010011001010011000 B

#88
b10000011111011111111001001110000 A
b10101100110001010011001010011000 B

#90
b10000011111011111111001001110000 A
b10100001100001110111000110110100 B

#92
b10000010011010010111001001101000 A
b10100001100001110111000110110100 B

#94
b01111101100101101000110110010111 A
b10100011100001110111000110010100 B

#96
b11101111000101000000010110000001 A
b10100011100001110111000110010100 B

#98
b11101111010101001000010110000101 A
b10100011100001110111000110010100 B

#100
b00111000110010110101001001111010 A
b10100011100001110111000110010100 B

#102
b11011010101110011111101011101011 A
b01011000011110001000111011101111 B

#104
b11011010101110011110101011101011 A
b10100111100001110111000100010000 B

#106
b11011010001110011110101011101011 A
b10100111100001110111000100010000 B

#108
b11011010001110011110101011101011 A
b01011001011110001000111011101111 B

#110
b00100101110001100001110100010000 A
b10100110100001110111000100010000 B

#112
b01011110011100100111111111000010 A
b01101101010100001001110011011111 B

#114
b01011110011100100111111111000010 A
b10110010101011110110001100100000 B

#116
b10100101000101011000000010010011 A
b01001101010000000001110011011111 B

#118
b01000111000000011111001001011101 A
b01001101010000000001110011011110 B

#120
b01000111000000011111001001011101 A
b10100011101100100101011110101001 B

#122
b10111000111111100000110110100010 A
b01001100010011011010100001010110 B

#124
b10010000111011100000110110100010 A
b01101110110011011010100001011110 B

#126
b10010000001010100011100110101010 A
b11101110110001011010000100000010 B

#128
b10010000001000100011100110101010 A
b10010011011000001101001111101001 B

#130
b10010001001110100011100110000000 A
b10010011011000001101001111101001 B

#132
b00001111000001010100011001111111 A
b01101100100111110010110000010110 B

#134
b11110000111110101011100110000000 A
b01101100100111110010110000010110 B

#136
b11111010011110010001010011010000 A
b10010011011000001101000111101001 B

#138
b11111010011110010101010011010000 A
b10000111111000000100101010100101 B

#140
b10111000110110100111100001001111 A
b10000111111000000100101010100101 B

#142
b10111000110110100111100001001111 A
b01111000000111111011010101011010 B

#144
b10111000110110100111110111001111 A
b01111101000111111011010101011010 B

#146
b00111000110111100111110110001111 A
b01111101000111100011010101101000 B

#148
b00111000110011110111110110101010 A
b01111100000111100011010101101000 B

#150
b01111000100010110111110110101010 A
b10000001011010011100101110010110 B

#152
b10000111111100101010001011110101 A
b01111110100100100111010001000001 B

#154
b01111001000011010101110100001010 A
b10111111100111010010000110011000 B

#156
b10010110111000101010000011110101 A
b10111111100111010010000110111000 B

#158
b01101001000111010101111100001010 A
b11011111100101010010000110111000 B

#160
b00011010111100100001000011110110 A
b01001011010011011111101001000011 B

#162
b10100000111001111110100011000010 A
b11010110000010001011101100010011 B

#164
b01011111000110000001011100111101 A
b10001110011101111001011100100011 B

#166
b10100000111001111010100011000010 A
b10000100101101110001011100110011 B

#168
b11100000111001010001100011100001 A
b01110111010110001110010010000100 B

#170
b00011111000110101110011100011110 A
b10001000101001110001101101111011 B

#172
b01011111000100111110011001101010 A
b10001000101001110001101101111011 B

#174
b01011111000100111110011001101010 A
b10001000101001110001111101111011 B

#176
b10100000111011000001100110010101 A
b10001000101001110001111101111011 B

#178
b01011111000100111110011001101010 A
b01110101011100001010000010000100 B

#180
b00100001011110001001110101010001 A
b01110101011110001010000010000100 B

#182
b00100001011110001001110101010001 A
b01101101110101111001000011000100 B

#184
b11011110100001110110001010101110 A
b10010010001010000110111100111011 B

#186
b00100001011110001001110101010001 A
b10010010001010000110111100111011 B

#188
b00100001011110001011110101010001 A
b01101101000101111001000011000100 B

#190
b10010000000111010000100011000011 A
b10110010011010000111110110111001 B

#192
b10010000000111010000100011000011 A
b00110111111000000010000010011001 B

#194
b10101000111000101011111010110101 A
b00010111111100010010001010111001 B

#196
b01101011110111110100110000010000 A
b00010111111100010010001010111001 B

#198
b10011110011000000001000110101011 A
b00010111011100010010001010111001 B

#200
b01100001100111111110111001010100 A
b11111010110010001101110101000110 B

#202
b01100001100111111110111001010100 A
b10000011001010110011001011101001 B

#204
b11000011000111110011001000011110 A
b11100101000111110100011111101001 B

#206
b00111100111000001100110111100001 A
b00011010111000001011100000010110 B

#208
b00111101111000011100110110100001 A
b00110100101100011011011111011111 B

#210
b11000010000111100011001001011110 A
b10100100101000011100001111101111 B

#212
b00111001111000011100110110100001 A
b01011011010111100011110000010000 B

#214
b00111010101001011000110101000001 A
b01011011010111100011110000010000 B

#216
b00111010101001011000110101000001 A
b10100100101000011100001111101111 B

#218
b11000101010110100111001010111110 A
b00011011011111100011110010010000 B

#220
b00111010101001011000110101000001 A
b10100100100000011100001101101111 B

#222
b11000001000111110111001001111011 A
b10000100100000011100001101101111 B

#224
b01000000000101110100001001110010 A
b10001100100110011100001111001101 B

#226
b01000110100101010001000110010110 A
b01110011011001100011110000110010 B

#228
b01000110100111010011001110010010 A
b01110011011001100011110000110010 B

#230
b01000110100111010011001110010010 A
b10001100100110011100001110001101 B

#232
b01000110100111010011001110010010 A
b01100010001101110001101001010000 B

#234
b10111001011000101100110001101101 A
b01100010001101110001101001010000 B

#236
b10111001011000101100110011100101 A
b01100110001001111000001001010000 B

#238
b01000110100111010111001100011010 A
b10011001110110000111110110101111 B

#240
b01000110100111010111001100011010 A
b01100110001001111000001001010000 B

#242
b10111001011000101000110011100101 A
b00011001110110111101110100000011 B

#244
b00101001101010111100110010010011 A
b00011001110110111101110100000011 B

#246
b10010110010000100011001101101100 A
b11100110001001000010001011111100 B

#248
b01001111001011001000111100000011 A
b00100100101001010101001010010101 B

#250
b01110101010111001110111111100101 A
b11011011010110101010110101101010 B

#252
b10001110101000100011000000010110 A
b11010001000011101000110101111010 B

#254
b11110001010111011101011111101001 A
b00101110111100010111001010000101 B

#256
b10110001010111011101011111001000 A
b11010001000011101000110101111010 B

#258
b10110001010111011101011111001000 A
b10010111000100110101101101001010 B

#260
b01001110101000100010100000110111 A
b11011101110101000011101101011110 B

#262
b11100101000011010001011011001110 A
b11011101010101000111111001010111 B

#264
b00011110101100101111100101110001 A
b11011001010101000111111001010010 B

#266
b00011110101100101111100101110001 A
b10001101100111001101101001110010 B

#268
b11111100011100010101100100101010 A
b10001101100111101101100111110010 B

#270
b11110100011000010101100100101010 A
b01110010011000010010011000001101 B

#272
b00101111110100010110011001000010 A
b10001101100110101111100111111010 B

#274
b00101111110100010110011001000010 A
b01110110111101000010001101010100 B

#276
b00111001110101110110101001000110 A
b10001001000010111101110010101011 B

#278
b00111101110101100110001101100110 A
b01110110001011001010011011010000 B

#280
b11000110111010011111110010011001 A
b10110100001011011010011010010100 B

#282
b11110101111010001101001010010101 A
b10110100001011011010011010010100 B

#284
b11110101111010001101001010010101 A
b01001011110100100101100101101011 B

#286
b11010101111110001101001010010101 A
b01001011110100100101100101101011 B

#288
b11010101111110001101001010010101 A
b00000101000101001000111010010100 B

#290
b11001110101110100011010011000111 A
b11111010111010110011000101101011 B

#292
b00100001110001011100101110111000 A
b11101111011001001010011110100001 B

#294
b11011110001110100011010001000111 A
b11101111011001001010011110100001 B

#296
b11011110001110100011010001000111 A
b11101010001000101100011111011001 B

#298
b10111000101010010000011101010010 A
b00011101110111010001100000100110 B

#300
b01000110010101101100100011111101 A
b00011101110111010001100000100110 B

#302
b00011001100100110001011111010010 A
b00011101110111010001100000100110 B

#304
b11100110011011001110100000101101 A
b01100010001000001110011011011001 B

#306
b11101111001111000010001100101101 A
b00001101110111110011100100000111 B

#308
b00010000110000111101110011010010 A
b11110010001001001100011011111000 B

#310
b11101110001101100010101100001101 A
b00101100111101111101100000000111 B

#312
b10111011110110111111010000100010 A
b00101100111101111101100000000111 B

#314
b01000100001101000001100101010101 A
b00100000110110010100010101110100 B

#316
b10111011110010111110011011101010 A
b11010111001001000011111000001011 B

#318
b10000000101101010001100100010101 A
b11110111001001000011111001001011 B

#320
b01111111010010101110011011101010 A
b11110111001001100011111101001011 B

#322
b10001011001111010100101110110001 A
b01001011101001000011011110101001 B

#324
b00110101111100110011010011101110 A
b01110000000111011100110001011110 B

#326
b01101101011001111000000010011100 A
b01010010010111011111110101011110 B

#328
b11110010100110000011111101101110 A
b11010000001010111110011101010110 B

#330
b11101100101001111101110001110001 A
b11010000001010111110011101010110 B

#332
b11101100101001111101110001110001 A
b11010000001010111010011000000010 B

#334
b11101100111001111101110001110001 A
b00101111110101000101100111111101 B

#336
b00010011000110000010001110001110 A
b11010000001010111010011000000010 B

#338
b11100000110000001101011001110001 A
b00100111110101000101101111111101 B

#340
b00011111001111110010100110001110 A
b00110100010001110111010111100100 B

#342
b00011111001111110010100110001110 A
b01100011111100001000111001001011 B

#344
b11100000100100001101011001110001 A
b01100011111100001000111001001011 B

#346
b00011111011011110010100110001110 A
b10010100010011110111000110110100 B

#348
b00001111011011110010100110001110 A
b01110000001111011001110001101101 B

#350
b00110100011000111010100011101100 A
b01110000001111011001110001101101 B

#352
b00110100011000111010100011101100 A
b00000111110000100111011011010010 B

#354
b11001011100111000101011100010011 A
b10101000001110011100100100101101 B

#356
b00110101011000111010100011101100 A
b10101000001110011100100100101101 B

#358
b11001010100111100101011100010111 A
b10101000001110011100000100101101 B

#360
b10001010100011110101011100010111 A
b10101000101110011100000100101101 B

#362
b10001010100011110001011100010111 A
b11010001101111001000111001101110 B

#364
b10001010100011110001011100010111 A
b00100010001010100110011110110100 B

#366
b11110101101100001010001010100000 A
b00110010111010100110001111100100 B

#368
b11011100001000010001011001001001 A
b11001101000101011001110000011011 B

#370
b00100011110111101110100110110110 A
b11011111010101001001111001111010 B

#372
b11011100001000010001011001001001 A
b00100000101010110110000110000101 B

#374
b10010100101100100000101001110100 A
b00100000101010110110000110000101 B

#376
b01101011010011011111010110001011 A
b11011111010101001001111001111010 B

#378
b10010100101100100000101001110100 A
b01001111110101001001011001111010 B

#380
b10100110001100110001111011100110 A
b01001110110100001001011001111010 B

#382
b01010001100011001110000100011001 A
b11100010000110001001011110111011 B

#384
b11010001100011001110000100011001 A
b11100010001110101001111010101010 B

#386
b11010001100011001110000100011001 A
b11100010001110101001111010101010 B

#388
b11101001101000010110010001110001 A
b00011101110001010110000101010101 B

#390
b11101001101000011110010001110001 A
b10001101111001010010101101110101 B

#392
b00010110010111100001101110001110 A
b01110010000110101101010010011010 B

#394
b00010110010110100001101110001110 A
b01111011000110101101010001011010 B

#396
b00010110010100100001101100001110 A
b10000100111001010010101110100101 B

#398
b00010110010100100001101100001110 A
b10000100111001010010101110100101 B

#400
b11101000101011111110000101011000 A
b01111011000110101101010001011010 B

#402
b00001101010101011100110000100011 A
b10000100111001010010101110100101 B

#404
b01001101010101011101100000100010 A
b01111011000110101101010001011010 B

#406
b10110010101010100010011111011101 A
b10000100111000010010101010100101 B

#408
b10110010101010100010011111011101 A
b01111010010111101101010111011011 B

#410
b10010010111010111010111111011101 A
b01111010010111101101010111011011 B

#412
b01101101000101000101000000100010 A
b01101100010001101010010111101001 B

#414
b01101101000101000101000000110001 A
b01000100001101000100110011100110 B

#416
b10010010111010111010011111001110 A
b11110010000010101111001100011001 B

#418
b01101101000111000101101000110001 A
b11110010000010101111001100011001 B

#420
b10010010111000110010010111001110 A
b11110010000010101111001100011001 B

#422
b10000000111001110110011001010011 A
b11000010011011111101110000001011 B

#424
b10000000111001110110011001010011 A
b11110010111011011101010100011111 B

#426
b10010000111000111110010001010001 A
b00001101000100100010101011100000 B

#428
b10010000111000111110010001010001 A
b01010111111001010101000100010011 B

#430
b11110001100000110110010001110000 A
b00100001110010001001010101000011 B

#432
b01010000100111100111101010110110 A
b01000001110010001011110100000011 B

#434
b01010000100111100111101010110110 A
b01000001110010001011110100000011 B

#436
b01111010101001011000000011001011 A
b11000001010011001011110100000011 B

#438
b01111010101001011000000011001011 A
b00111110101100110100001011111100 B

#440
b10000101010110100111111100110100 A
b10110010110011100100000111010101 B

#442
b01111010100001001000000101001100 A
b10110011110011110000011100011101 B

#444
b10000101011110110111111010110011 A
b01111011110010100001111000011000 B

#446
b10000101011100100011111010111111 A
b10000100001101011110000111100111 B

#448
b01111010100011011101000101000000 A
b01101110100100100000000100101111 B

#450
b01111010100011011101000101000000 A
b11110001011110011000110011010100 B

#452
b10000101011100100010111010111111 A
b00001110100001100111001100101011 B

#454
b00101011110000010000111110111110 A
b00001111100001100111100100101011 B

#456
b11010111101110100011000000000001 A
b01011110101001100111100100101010 B

#458
b11010111101110100011000000000001 A
b01011110101001100111100100101010 B

#460
b11010111101110100011000000000001 A
b01011000000010000101000100111000 B

#462
b11010111101110100011000000100001 A
b00101111111101111010111011000110 B

#464
b11010111101110100011000000100001 A
b11010100000010000101001100111000 B

#466
b11011001001110100100000000000001 A
b00011010001100111010011001000101 B

#468
b00100110110001011011111111111110 A
b11100101111110101101100100111111 B

#470
b00011001000011110100001000010001 A
b00011010011001010010011111010000 B

#472
b00011001000011110100001000010001 A
b11100101100110101101100000101111 B

#474
b11101110111100001011110111101110 A
b00001111110010001100100101101111 B

#476
b00010001000011110100001000010001 A
b00001111110010001100100101101111 B

#478
b11101110111101001011110111101110 A
b00001111111010001100100101101111 B

#480
b11101110111111100010000111010110 A
b11110101000101010011011010011000 B

#482
b10111111110111000001010111010110 A
b11110101000101110011011010011000 B

#484
b01100111110011101011110011001110 A
b11110101000101110011011010011000 B

#486
b01100011100110101011110011001110 A
b11110101000101110011011010011000 B

#488
b01110001111010001100011100101001 A
b11110101000101110011011010011000 B

#490
b10001110000101110011100011010110 A
b00001010111010001100100101100111 B

#492
b01100001111010001100111100101001 A
b00011111110010000001110000111111 B

#494
b10011110000101110011000011010110 A
b11100000001101111110001111000000 B

#496
b01111101011010001100111110100001 A
b11100000001101111110001111000000 B

#498
b10000010100101110011000001011110 A
b00011111110010000101110010111111 B

#500
b10000010100101110011000001011110 A
b11100000001101111010001101000000 B

#502
b01111101011010001100111110100001 A
b00011111100110000111110001011111 B

#504
b00000010011110010011000011010110 A
b00011111100110000111110001011111 B

#506
b11110111100001001100101100101100 A
b00001010000111000101011001010101 B

#508
b10110111000110101000101111011100 A
b00000011000111000101011001010101 B

#510
b10110111000110101000101111011100 A
b00000011000111000101011001010101 B

#512
b01010000111001010111010000100111 A
b11111100111000111010100110101010 B

#514
b10101111000110001100101111011000 A
b01010011001001010001011001011100 B

#516
b01010000111001110011010000100111 A
b00010011011000010101111001011101 B

#518
b10101111010110000100100111011000 A
b00010011011000010101110001011101 B

#520
b10101111010110000100100111011000 A
b01000001111000011100111000111001 B

#522
b01110110011111100011011010100111 A
b10001111100001100110101000011010 B

#524
b01110110011111100011011010100111 A
b10001111100001100110101000011010 B

#526
b01110110011111100011011010100111 A
b10001111100001100110101000011010 B

#528
b01110110011111100011011010100111 A
b10001100100001100010101000011010 B

#530
b01110110011111100011011010100111 A
b01000011011110001111110101110101 B

