verilog/adder_struct.v
// carry look ahead adder
module adder (A, B, Cin, S, P, G, Cout, OVF);

	////////
	// IO //
	////////
  input  [31:0]  A, B;
  input          Cin;
  output [31:0]	 S, P, G;
  output Cout, OVF;

	////////////////////
	// Internal Nodes //
	////////////////////
	reg    [31:0]  carrychain;
  
	// P, G
	assign G = A & B; // carry generate
  assign P = A ^ B; // carry propagate
  
	// Carry Chain
  always @(*)
    begin : carry_generation
      integer i;
      carrychain[0] = G[0] + (P[0] & Cin);
      for(i = 1; i <= 31; i = i + 1)
        begin
          carrychain[i] = G[i] + (P[i] & carrychain[i-1]);
        end
    end

	/* should redo this so we don't get a ripple carry adder
	// 8 4-bit CLAs that interface directly with the bits
	CLA cla_0 ();
	CLA cla_0 ();
	CLA cla_0 ();
	CLA cla_0 ();
	CLA cla_0 ();
	CLA cla_0 ();
	CLA cla_0 ();
	CLA cla_0 ();
		
	// 2 MS 4-bit CLAs that interface with the lower level CLAs
	CLA cla_0 ();
	CLA cla_0 ();
	*/
	
	// Sum
  wire [32:0] shiftedcarry;

	assign shiftedcarry = {carrychain,Cin};
  assign S = P ^ shiftedcarry[31:0];    // summation
  
	// Carry Out
	assign Cout = shiftedcarry[32];
	
	// Overflow
	assign OVF = shiftedcarry[32] ^ shiftedcarry[31];

endmodule

/* not currently used
// Carry Look-Ahead Unit
module CLA (P, G, C, Cout, Pin, Gin, Cin);

	// I/O
	output	[3:0] C;
	output				Cout, P, G;
	input		[3:0] Pin, Gin;
	input					Cin;
	
	assign C[0] = Cin;
	assign C[1] = Gin[0] + (Pin[0] & Cin);
	assign C[2] = Gin[1] + (Pin[1] & Gin[0]) + (Pin[1] & Pin[0] & Cin);
	assign C[3] = Gin[2] + (Pin[2] & Gin[1]) + (Pin[2] & Pin[1] & Gin[0]) + (Pin[2] & Pin[1] & Pin[0] & Cin);
	assign Cout = Gin[3] + (Pin[3] & Gin[2]) + (Pin[3] & Pin[2] & Gin[1]) + (Pin[3] & Pin[2] & Pin[1] & Gin[0]) + (Pin[3] & Pin[2] & Pin[1] & Pin[0] & Cin);
	
	assign P = &Pin;
	assign G = Gin[3] + Pin[3] & Gin[2] + Pin[3] & Pin[2] & Gin[1] + Pin[3] & Pin[2] & Pin[1] & Gin[0];
	
endmodule
*/

verilog/Alu.v
`timescale 1ns / 10 ps
`include "adder_struct.v"

module Alu( Z, A, B, DI, DO, CI, INST, FLAGS, FirstCyc );
input [31:0] A;
input [31:0] B;
input [31:0] DI;
input [3:0] INST;
input CI;
input FirstCyc;
output [31:0] Z;
output [31:0] DO;
output [3:0] FLAGS;
wire  dpa_zero, dpa_one;
wire [3:0] Z_Inst_Z1_, Z_Inst_, Z_BInst_X1_, Z_BInst_;
wire [31:0] Z_AS_, Z_BS_;
wire  Z_passA_, Z_BINVERT__4_, Z_BINVERT_, Z_BCARRY__5_, Z_BCARRY__6_,
     Z_BCARRY_, Z_AS0_, const_1_1_, Z_AS1_, const_2_1_, Z_AS2_, Z_AS3_;
reg [1:0] Z_ASIGN__8_;
wire  const_3_0_;
reg  Z_ASIGN_;
wire  const_4_0_;
reg [31:0] Z_BIN_;
wire [31:0] Z_BI1_, Z_AIN_, Z_AI_;
wire  Z_CarryIn__9_, Z_CarryIn__10_, Z_CarryIn__11_;
reg  Z_CarryIn_;
wire [2:0] const_5_6_;
wire  const_6_1_, Z_DIVIDE_, Z_BI__14_;
wire [31:0] Z_BI_Z1_, Z_BI__13_;
wire  Z_BI__15_;
reg [31:0] Z_BI_;
wire [32:0] Z_SUM_, Z_Z0_, Z_Z1_, Z_Z2_, Z_Z3_, Z_Z4_, Z_Z5_, Z_Z6_, Z_Z7_,
     Z_AdderOutN_;
wire [31:0] Z_BA_X1_, Z_BA_, Z_BB_X1_, Z_BB_;
wire [32:0] Z_Z8_, Z_Z9_, Z_Z10_, Z_Z11_, Z_Z12_, Z_Z13_;
wire  const_7_0_;
wire [32:0] Z_Z14_;
wire  const_8_1_;
wire [32:0] Z_Z15_;
reg [31:0] Z_ZB_;
wire [31:0] Z_ZC__16_;
reg [31:0] Z_ZC_;
wire [31:0] Z_1_;
wire  Z_C_, Z_OVF_, Z_CarryF_, Z_ZeroF__17_, Z_ZeroF_, const_9_0_;
wire [3:0] FLAGS_Z1_, FLAGS_3_;
wire [31:0] DO_Z1_, DO_2_;
assign dpa_zero= 1024'h0;
assign dpa_one= 1024'h1;
assign const_1_1_= 1024'h1;
assign const_2_1_= 1024'h1;
assign const_3_0_= 1024'h0;
assign const_4_0_= 1024'h0;
assign const_5_6_= 1024'h6;
assign const_6_1_= 1024'h1;
assign const_7_0_= 1024'h0;
assign const_8_1_= 1024'h1;
assign const_9_0_= 1024'h0;

assign Z_Inst_Z1_={ INST[3],INST[2],INST[1],INST[0]};

assign Z_Inst_= (Z_Inst_Z1_[3:0]);

assign Z_BInst_X1_ = Z_Inst_[3:0];

assign Z_BInst_ = Z_BInst_X1_[3:0];

assign Z_AS_= (A[31:0]);

assign Z_BS_= (B[31:0]);

assign Z_passA_= (Z_Inst_[2]&Z_Inst_[1]&Z_Inst_[0]);

assign Z_BINVERT__4_= (Z_Inst_[2]&~Z_Inst_[1]);

assign Z_BINVERT_= (Z_Inst_[0]&~Z_BINVERT__4_);

assign Z_BCARRY__5_= (Z_Inst_[0]&Z_Inst_[1]);

assign Z_BCARRY__6_= (~Z_Inst_[0]&~Z_Inst_[1]&~Z_Inst_[2]);

assign Z_BCARRY_= (Z_BCARRY__5_|Z_BCARRY__6_);

assign Z_AS0_= (Z_AS_[31]);

assign Z_AS1_= (const_1_1_);

assign Z_AS2_= (A[31]-B[31]-const_2_1_+1 == (2'b0<<0));

assign Z_AS3_= (Z_AS2_);
always @ (Z_Inst_[1:0]  or Z_AS2_ or Z_AS1_ or Z_AS0_) begin
	case (Z_Inst_[1:0])
		2'd2: Z_ASIGN__8_ = (Z_AS2_);
		2'd1: Z_ASIGN__8_ = (Z_AS1_);
		2'd0: Z_ASIGN__8_ = (Z_AS0_);
		default: Z_ASIGN__8_ = 2'bx;
	endcase
end
always @ (Z_BInst_[2]  or Z_ASIGN__8_ or const_3_0_) begin
	case (Z_BInst_[2])
		1'd1: Z_ASIGN_ = ~(Z_ASIGN__8_[1:0]);
		1'd0: Z_ASIGN_ = ~(const_3_0_);
		default: Z_ASIGN_ = 1'bx;
	endcase
end
always @ (Z_BInst_[1]  or Z_BS_ or const_4_0_) begin
	case (Z_BInst_[1])
		1'd1: Z_BIN_ = ~(Z_BS_[31:0]);
		1'd0: Z_BIN_ = ~(const_4_0_);
		default: Z_BIN_ = 32'bx;
	endcase
end

assign Z_BI1_= (Z_BIN_[31:0]^(-Z_BINVERT_));

assign Z_AIN_= (Z_AS_[31:0]^(-Z_ASIGN_));

assign Z_AI_= (~Z_AIN_[31:0]&~(-Z_passA_));

assign Z_CarryIn__9_= ((-Z_BCARRY_)|~(-Z_ASIGN_));

assign Z_CarryIn__10_= (~(-Z_CarryIn__9_));

assign Z_CarryIn__11_= (~CI);
always @ (FirstCyc  or Z_CarryIn__10_ or Z_CarryIn__11_) begin
	case (FirstCyc)
		1'd1: Z_CarryIn_ = ~((-Z_CarryIn__10_));
		1'd0: Z_CarryIn_ = ~(Z_CarryIn__11_);
		default: Z_CarryIn_ = 1'bx;
	endcase
end

assign Z_DIVIDE_= (Z_Inst_[3:0]-const_5_6_[2:0]-const_6_1_+1 == (5'b0<<0));

assign Z_BI__14_= (~DI[31]);

assign Z_BI_Z1_={ Z_BI1_[30:0],Z_BI__14_};

assign Z_BI__13_= (Z_BI_Z1_[31:0]);

assign Z_BI__15_= (~Z_DIVIDE_);
always @ (Z_BI__15_  or Z_BI1_ or Z_BI__13_) begin
	case (Z_BI__15_)
		1'd1: Z_BI_ = ~(Z_BI1_[31:0]);
		1'd0: Z_BI_ = ~(Z_BI__13_[31:0]);
		default: Z_BI_ = 32'bx;
	endcase
end


//adder//
//assign Z_SUM_= (Z_BI_[31:0]+Z_AI_[31:0]+Z_CarryIn_);
adder a1(Z_AI_,Z_BI_,Z_CarryiIn_,Z_SUM_[31:0],Z_SUM_[32]);


/*assign Z_Z0_= (Z_SUM_[32:0]);

assign Z_Z1_= (Z_Z0_[32:0]);

assign Z_Z2_= (Z_Z0_[32:0]);

assign Z_Z3_= (Z_Z0_[32:0]);

assign Z_Z4_= (Z_Z0_[32:0]);

assign Z_Z5_= (Z_Z0_[32:0]);

assign Z_Z6_= (Z_Z0_[32:0]);

assign Z_Z7_= (Z_Z0_[32:0]);
*/

//assign Z_AdderOutN_= (~Z_Z0_[32:0]);
assign Z_AdderOutN_ = (~Z_SUM_[32:0]);

assign Z_BA_X1_ = Z_AS_[31:0];

assign Z_BA_ = Z_BA_X1_[31:0];

assign Z_BB_X1_ = Z_BS_[31:0];

assign Z_BB_ = Z_BB_X1_[31:0];

assign Z_Z8_= (Z_BA_[31:0]&Z_BB_[31:0]);

assign Z_Z9_= (Z_BA_[31:0]|Z_BB_[31:0]);

assign Z_Z10_= (Z_BA_[31:0]^Z_BB_[31:0]);

assign Z_Z11_= (~Z_BB_[31:0]);

assign Z_Z12_= (Z_BA_[31:0]);

assign Z_Z13_= (~Z_BA_[31:0]);

assign Z_Z14_= (const_7_0_);

assign Z_Z15_= (const_8_1_);
always @ (Z_BInst_[2:0]  or Z_Z15_ or Z_Z14_ or Z_Z13_ or Z_Z12_ or Z_Z11_
     or Z_Z10_ or Z_Z9_ or Z_Z8_) begin
	case (Z_BInst_[2:0])
		3'd7: Z_ZB_ = (Z_Z15_[32:0]);
		3'd6: Z_ZB_ = (Z_Z14_[32:0]);
		3'd5: Z_ZB_ = (Z_Z13_[32:0]);
		3'd4: Z_ZB_ = (Z_Z12_[32:0]);
		3'd3: Z_ZB_ = (Z_Z11_[32:0]);
		3'd2: Z_ZB_ = (Z_Z10_[32:0]);
		3'd1: Z_ZB_ = (Z_Z9_[32:0]);
		3'd0: Z_ZB_ = (Z_Z8_[32:0]);
		default: Z_ZB_ = 32'bx;
	endcase
end

assign Z_ZC__16_= (~Z_ZB_[31:0]);
always @ (Z_BInst_[3]  or Z_ZC__16_ or Z_AdderOutN_) begin
	case (Z_BInst_[3])
		1'd1: Z_ZC_ = ~(Z_ZC__16_[31:0]);
		1'd0: Z_ZC_ = ~(Z_AdderOutN_[32:0]);
		default: Z_ZC_ = 32'bx;
	endcase
end

assign Z_1_= (Z_ZC_[31:0]);

assign Z_C_= (~Z_AdderOutN_[32]);

assign Z_OVF_= (Z_AI_[31]^Z_BI_[31]^Z_AdderOutN_[32]^Z_AdderOutN_[31]);

assign Z_CarryF_= (Z_C_);

assign Z_ZeroF__17_= (Z_1_[0]|Z_1_[1]|Z_1_[2]|Z_1_[3]|Z_1_[4]|Z_1_[5]|Z_1_[6]
    |Z_1_[7]|Z_1_[8]|Z_1_[9]|Z_1_[10]|Z_1_[11]|Z_1_[12]|Z_1_[13]|Z_1_[14]
    |Z_1_[15]|Z_1_[16]|Z_1_[17]|Z_1_[18]|Z_1_[19]|Z_1_[20]|Z_1_[21]|Z_1_[22]
    |Z_1_[23]|Z_1_[24]|Z_1_[25]|Z_1_[26]|Z_1_[27]|Z_1_[28]|Z_1_[29]|Z_1_[30]
    |Z_1_[31]);

assign Z_ZeroF_= (~Z_ZeroF__17_);

assign FLAGS_Z1_={ const_9_0_,Z_ZeroF_,Z_CarryF_,Z_OVF_};

assign FLAGS_3_= (FLAGS_Z1_[3:0]);

assign DO_Z1_={ DI[30:0],Z_C_};

assign DO_2_= (DO_Z1_[31:0]);

assign Z = Z_1_[31:0];

assign DO = DO_2_[31:0];

assign FLAGS = FLAGS_3_[3:0];

/*User Defined Aliases */
endmodule

pt_scripts/test.vcd
$date
        Mon Mar 20 11:53:20 2006
$end

$version
        Synopsys VCS version 7.2.1
$end

$timescale
        1ns
$end

$scope module Alu $end
$var wire 32 A A [31:0] $end
$var wire 32 B B [31:0] $end
$var wire 1 C CI $end
$var wire 32 D DI [31:0] $end
$var wire 1 F FirstCyc $end
$var wire 4 I INST [3:0] $end

$upscope $end

$enddefinitions $end

#0
$dumpvars
b00000000000000000000000000000000 A
b00000000000000000000000000000000 B
b00000000000000000000000000000000 D
b0000 I
0C
0F
$end


#2
b00000000000000000000000000000000 A
b00000000000000000000000000000000 B

#4
b00000000000000000000000000000001 A
b00000000000000000000000000000000 B

#6
b11111111111111111111111111111111 B
b00000000000000000000000000000001 A

#8
b11111111111111111111111111111111 B
b00000000000000000000000000000000 A

#10
b00000000000000000000000000000001 B
b00000000000000000000000000000000 A

#12
b00000000000000000000000000000001 B
b00000000000000000000000000000001 A

#14
b00000000000000000000000000000000 A
b10000000000000000000000000000000 B
#16
b00010000000000000000000000000000 A
b00000101011100111111111111111111 B
#18
b00000000000000000000000000000000 A
b00000000000000000000000000000000 B
#20
b00010011011010011111111111111111 A
b01110010010010001000111111111111 B
#22
b00010000000000000000000000000000 A
b00010000000000000000000000000000 B
#24
b10000000000000000000000000000000 A
b00010000000000000000000000000000 B
#26
b10000000000000000000000000000000 A
b01101000110010111111111100100000 B
#28
b01101001101010001011011111111111 A
b01110110001111110111100111111111 B
#30
b00000000000000000000000000000000 A
b00010000000000000000000000000000 B
#32
b00000000000000000000000000000000 A
b00000000000000000000000000000000 B
#34
b10100110001001011111111111111111 A
b00000000000000000000000000000000 B
#36
b00000000000000000000000000000000 A
b01110011011010001111101011100000 B
#38
b10001011100101100110010111101111 A
b10000000000000000000000000000000 B
#40
b00000000000000000000000000000000 A
b10101110001101010111011111111111 B
#42
b00010000000000000000000000000000 A
b00000000000000000000000000000000 B
#44
b01000010011101111111111111111111 A
b01101100011011001100000000000000 B
#46
b00111100101110111111111111111111 A
b00101110011011010000100000000000 B
#48
b01101001101111011111111111111111 A
b10000000000000000000000000000000 B
#50
b11110011101010011111111111111111 A
b00000000000000000000000000000000 B
#52
b00110010101110111011000010100000 A
b00000000000000000000000000000000 B
#54
b00000000000000000000000000000000 A
b10000000000000000000000000000000 B
#56
b01110101111111011111111111111111 A
b00000000000000000000000000000000 B
#58
b00100011100110101101001101111111 A
b00000000000000000000000000000000 B
#60
b00010000000000000000000000000000 A
b01111110000010000010101010100000 B
#62
b00000000000000000000000000000000 A
b00000000000000000000000000000000 B
#64
b00010000000000000000000000000000 A
b00010000000000000000000000000000 B
#66
b00010000000000000000000000000000 A
b00000000000000000000000000000000 B
#68
b00001011011101101000100000000000 A
b00111110011011111111111111111111 B
#70
b00000000000000000000000000000000 A
b11010001111110011111111111111111 B
#72
b00001101111001111001110110001000 A
b01010011111001000110111100010000 B
#74
b00010000000000000000000000000000 A
b10000000000000000000000000000000 B
#76
b00000000000000000000000000000000 A
b10000111101110111111111111111111 B
#78
b00000000000000000000000000000000 A
b00000000000000000000000000000000 B
#80
b10000000000000000000000000000000 A
b00000000000000000000000000000000 B
#82
b10111010110110011111111111111111 A
b01111010011010011111111111111111 B
#84
b00000000000000000000000000000000 A
b10000000000000000000000000000000 B
#86
b00010000000000000000000000000000 A
b10000000000000000000000000000000 B
#88
b00000011111011001001000000000000 A
b10011101111100000000011110100000 B
#90
b00000000000000000000000000000000 A
b11011011001001011001111111111111 B
#92
b10000000000000000000000000000000 A
b01011011001010111111111111111111 B
#94
b00000000000000000000000000000000 A
b00010000000000000000000000000000 B
#96
b01010010000000000000000000000000 A
b10001001101100111111111111111111 B
#98
b10000000000000000000000000000000 A
b00110110001000100011010101001000 B
#100
b00010000000000000000000000000000 A
b00010000000000000000000000000000 B
#102
b01011001010100111111111111111111 A
b00010000000000000000000000000000 B
#104
b01100110010110111111111111111111 A
b00001101001101011011001001010000 B
#106
b10000110111011011111111111111111 A
b00000000000000000000000000000000 B
#108
b00000000000000000000000000000000 A
b00010000000000000000000000000000 B
#110
b00000000000000000000000000000000 A
b10000000000000000000000000000000 B
#112
b00011011010011111111111111111111 A
b01011011001010111111111111111111 B
#114
b00000000000000000000000000000000 A
b01001110010100010110111111111111 B
#116
b11010010100110100000101100110000 A
b10000010001101011011001010110000 B
#118
b00010000000000000000000000000000 A
b10111010110101100001101111100000 B
#120
b10000000000000000000000000000000 A
b00010000000000000000000000000000 B
#122
b00111100011001010010110010000000 A
b10000111000100010101110110001000 B
#124
b00000000000000000000000000000000 A
b00000000000000000000000000000000 B
#126
b00000000000000000000000000000000 A
b00011010110110010101110110111111 B
#128
b00000000000000000000000000000000 A
b00010000000000000000000000000000 B
#130
b00011011100110010101001001010000 A
b10100011101011011111111111111111 B
#132
b00010000100101111111111111111111 A
b10000000000000000000000000000000 B
#134
b00000000000000000000000000000000 A
b10000000000000000000000000000000 B
#136
b10000111101110111111111111111111 A
b00111110000010011111111111111111 B
#138
b00000000000000000000000000000000 A
b00010000000000000000000000000000 B
#140
b11000010001000010111111011101000 A
b00000000000000000000000000000000 B
#142
b10100110001001011111111111111111 A
b00010000000000000000000000000000 B
#144
b00010000000000000000000000000000 A
b00010000000000000000000000000000 B
#146
b00010000000000000000000000000000 A
b00010000000000000000000000000000 B
#148
b00010000000000000000000000000000 A
b00011101000001010111011111111111 B
#150
b00000000000000000000000000000000 A
b00000000000000000000000000000000 B
#152
b00010000000000000000000000000000 A
b00000000000000000000000000000000 B
#154
b00010000000000000000000000000000 A
b00101010110101000101111111111111 B
#156
b00000000000000000000000000000000 A
b00010000000000000000000000000000 B
#158
b00000000000000000000000000000000 A
b00010000000000000000000000000000 B
#160
b00010000000000000000000000000000 A
b00011011100100001110111111111111 B
#162
b01010001000111101100010110100000 A
b11010101110101011111111111111111 B
#164
b00100010101000111111111111111111 A
b10000000000000000000000000000000 B
#166
b00000000000000000000000000000000 A
b00010000000000000000000000000000 B
#168
b00010000000000000000000000000000 A
b00010000000000000000000000000000 B
#170
b00000000000000000000000000000000 A
b00000000000000000000000000000000 B
#172
b00010000000000000000000000000000 A
b00000000000000000000000000000000 B
#174
b00010000000000000000000000000000 A
b10011110101111111000101001010000 B
#176
b00010000000000000000000000000000 A
b00010000000000000000000000000000 B
#178
b00000000000000000000000000000000 A
b01010001000111101100010110100000 B
#180
b10000000000000000000000000000000 A
b01000110000000000000000000000000 B
#182
b10001100110010011111111111111111 A
b10000000000000000000000000000000 B
#184
b00010000000000000000000000000000 A
b00010000000000000000000000000000 B
#186
b00010000000000000000000000000000 A
b00000000000000000000000000000000 B
#188
b10000000000000000000000000000000 A
b10011100011110111111111111111111 B
#190
b00111011101100011111111111111111 A
b00101100110000111111111111111111 B
#192
b10000000000000000000000000000000 A
b00000000000000000000000000000000 B
#194
b00000000000000000000000000000000 A
b01110110001111110111100111111111 B
#196
b00010000000000000000000000000000 A
b10000000000000000000000000000000 B
#198
b00010000000000000000000000000000 A
b00000000000000000000000000000000 B
#200
b00000000000000000000000000000000 A
b00000000000000000000000000000000 B
#202
b00000000000000000000000000000000 A
b00011110010110111011001011111111 B
#204
b10000000000000000000000000000000 A
b11000001010100111111111111111111 B
#206
b00010000000000000000000000000000 A
b00000000000000000000000000000000 B
#208
b10000000000000000000000000000000 A
b10000000000000000000000000000000 B
#210
b00010000000000000000000000000000 A
b00011001111011001011011111111111 B
#212
b10000000000000000000000000000000 A
b00011111111101111101111100000000 B
#214
b11000001010100111111111111111111 A
b00000000000000000000000000000000 B
#216
b10000000000000000000000000000000 A
b00010000000000000000000000000000 B
#218
b00010000000000000000000000000000 A
b01010010000111011111111111111111 B
#220
b00010000100101111111111111111111 A
b00000000000000000000000000000000 B
#222
b01000100100001111111111111111111 A
b00000000000000000000000000000000 B
#224
b00010000000000000000000000000000 A
b00111101101111101101101001111111 B
#226
b10100011011011101100111111111111 A
b00110000110011010111111001010000 B
#228
b00010000000000000000000000000000 A
b01111010110001011001001110011000 B
#230
b10000000000000000000000000000000 A
b11000110110110011111111111111111 B
#232
b00000000000000000000000000000000 A
b11101111101110111111111111111111 B
#234
b10000000000000000000000000000000 A
b00000000000000000000000000000000 B
#236
b00000000000000000000000000000000 A
b10000000000000000000000000000000 B
#238
b00010000000000000000000000000000 A
b01000011010111101101110100110111 B
#240
b00001010100110011111111111111111 A
b10000000000000000000000000000000 B
#242
b00000000000000000000000000000000 A
b00100010000100000000001011001000 B
#244
b00110001101101001011011101010000 A
b00010000000000000000000000000000 B
#246
b00000000000000000000000000000000 A
b00000000000000000000000000000000 B
#248
b00010011011010011111111111111111 A
b01101000001100111111111111111111 B
#250
b11000000110100111011011111111111 A
b00000000000000000000000000000000 B
#252
b00011011101010111111111111111111 A
b00000000000000000000000000000000 B
#254
b00000000000000000000000000000000 A
b10000000000000000000000000000000 B
#256
b00100010110100101110111111111111 A
b00010000000000000000000000000000 B
#258
b00000000000000000000000000000000 A
b11110000111111111111111111111111 B
#260
b01111010001111000110111011001000 A
b10000000000000000000000000000000 B
#262
b11010111011001111010001001001000 A
b11100110110110111111111111111111 B
#264
b11110111010011011111111111111111 A
b00000000000000000000000000000000 B
#266
b11000110110110011111111111111111 A
b10101110001101010111011111111111 B
#268
b00101100100100111111111111111111 A
b00000000000000000000000000000000 B
#270
b00000000000000000000000000000000 A
b00010000000000000000000000000000 B
#272
b10000110110010100011110101010000 A
b10100011111111001011100101001000 B
#274
b00000000000000000000000000000000 A
b00000000000000000000000000000000 B
#276
b00010000000000000000000000000000 A
b01110110000000000000000000000000 B
#278
b00111010101010011111111111111111 A
b00000000000000000000000000000000 B
#280
b00010000000000000000000000000000 A
b00000111100011111111111111111111 B
#282
b01010001110010101000100000000000 A
b00011011100110010101001001010000 B
#284
b00000000000000000000000000000000 A
b00010000000000000000000000000000 B
#286
b10000000000000000000000000000000 A
b00010000000000000000000000000000 B
#288
b00010000000000000000000000000000 A
b00010000000000000000000000000000 B
#290
b01000110000010011111111111111111 A
b00000000000000000000000000000000 B
#292
b01111100101000010010001011001000 A
b10000000000000000000000000000000 B
#294
b10000000000000000000000000000000 A
b00000000000000000000000000000000 B
#296
b00000000000000000000000000000000 A
b00100010001101010100100000000000 B
#298
b01000010000000000000000000000000 A
b00010000000000000000000000000000 B
#300
b00101100100100111111111111111111 A
b00100010000000000000000000000000 B
#302
b00000000000000000000000000000000 A
b10000000000000000000000000000000 B
#304
b00011010110110010101110110111111 A
b00001010100110011111111111111111 B
#306
b10010111111111111111111111111111 A
b00000000000000000000000000000000 B
#308
b00000000000000000000000000000000 A
b11001111001101011100000111110000 B
#310
b00101011100010100001011001011000 A
b00000000000000000000000000000000 B
#312
b10011110010000111111111111111111 A
b00010000000000000000000000000000 B
#314
b11010001100100101111011111111111 A
b11000000101000001010111111111111 B
#316
b10000000000000000000000000000000 A
b01001000000001000010110000110000 B
#318
b11010001100100101111011111111111 A
b00111110010100101001110011011000 B
#320
b00000000000000000000000000000000 A
b00000000000000000000000000000000 B
#322
b10000000000000000000000000000000 A
b11100001011010011111111111111111 B
#324
b01110101111111011111111111111111 A
b11111100000100110110111111111111 B
#326
b11111011101001100110101111111111 A
b00101000100100011110000000000000 B
#328
b00000000000000000000000000000000 A
b10000000000000000000000000000000 B
#330
b00111011100101100001111011101000 A
b00000000000000000000000000000000 B
#332
b10000100100000001111001111010000 A
b11101110000001110011010010010000 B
#334
b00000000000000000000000000000000 A
b00000000000000000000000000000000 B
#336
b01110100110110111111111111111111 A
b00000000000000000000000000000000 B
#338
b00000000000000000000000000000000 A
b00000000000000000000000000000000 B
#340
b11110010011110111111111111111111 A
b11101010010100111111111111111111 B
#342
b10111110110110100111111111111111 A
b10100001100101011111111111111111 B
#344
b00000000000000000000000000000000 A
b00010000000000000000000000000000 B
#346
b00010000000000000000000000000000 A
b11000000101000001010111111111111 B
#348
b01111010011010011111111111111111 A
b00000000000000000000000000000000 B
#350
b00000000000000000000000000000000 A
b00001110011000011111110000000000 B
#352
b00010000000000000000000000000000 A
b10000000000000000000000000000000 B
#354
b10000000000000000000000000000000 A
b00010000000000000000000000000000 B
#356
b00011100100010110111111111111111 A
b00000101100100110101111111111111 B
#358
b00000000000000000000000000000000 A
b01011110010101011011111001100000 B
#360
b01010100111011011111111111111111 A
b11001111101101001001000000000000 B
#362
b10000000000000000000000000000000 A
b00000000000000000000000000000000 B
#364
b00000000000000000000000000000000 A
b10101110001101010111011111111111 B
#366
b10110100001010101011010011011000 A
b00010000000000000000000000000000 B
#368
b11110110010111001001000100110000 A
b00000000000000000000000000000000 B
#370
b00010100001010110000100111000000 A
b01001011110001000011011101110000 B
#372
b00010000000000000000000000000000 A
b00010000000000000000000000000000 B
#374
b10000000000000000000000000000000 A
b01001101011101011001111111111111 B
#376
b10000000000000000000000000000000 A
b00010000000000000000000000000000 B
#378
b00000000000000000000000000000000 A
b00000000000000000000000000000000 B
#380
b00000000000000000000000000000000 A
b00000000000000000000000000000000 B
#382
b00010000000000000000000000000000 A
b00001010100110011111111111111111 B
#384
b00000000000000000000000000000000 A
b10000000000000000000000000000000 B
#386
b00010000000000000000000000000000 A
b00101100100100111111111111111111 B
#388
b00010000000000000000000000000000 A
b00111011111110011111111111111111 B
#390
b00001010001000111111111111111111 A
b10010011111001010100000000000000 B
#392
b01010000110001111111111111111111 A
b00110110010010011111111111111111 B
#394
b10000100000110011000110001100000 A
b00010000000000000000000000000000 B
#396
b01101011100000001000011000110000 A
b10100011101011011111111111111111 B
#398
b00000000000000000000000000000000 A
b10000000000000000000000000000000 B
#400
b11110100011010011001101000010000 A
b00000000000000000000000000000000 B
#402
b11000001111110101110010100011000 A
b00010000000000000000000000000000 B
#404
b00000000000000000000000000000000 A
b00010000000000000000000000000000 B
#406
b00000000000000000000000000000000 A
b00000000000000000000000000000000 B
#408
b00000000000000000000000000000000 A
b00010000000000000000000000000000 B
#410
b10000000000000000000000000000000 A
b01011001100101000000000000000000 B
#412
b10011110010000111111111111111111 A
b00010000000000000000000000000000 B
#414
b00000000000000000000000000000000 A
b10000000000000000000000000000000 B
#416
b00000000000000000000000000000000 A
b01001110001110111010111111111111 B
#418
b00000000000000000000000000000000 A
b01010000110111101100111011100000 B
#420
b10000000000000000000000000000000 A
b11010001111110011111111111111111 B
#422
b00010000000000000000000000000000 A
b00000000000000000000000000000000 B
#424
b00100000100111111111111111111111 A
b00000000000000000000000000000000 B
#426
b00000000000000000000000000000000 A
b00000000000000000000000000000000 B
#428
b00000110010101101111010010010000 A
b00010000000000000000000000000000 B
#430
b00010000000000000000000000000000 A
b00000000000000000000000000000000 B
#432
b00001000001111000100100000000000 A
b10100001100101011111111111111111 B
#434
b10000000000000000000000000000000 A
b00101110011001110100100111000000 B
#436
b00000000000000000000000000000000 A
b01001000000001000010110000110000 B
#438
b10000000000000000000000000000000 A
b00000000000000000000000000000000 B
#440
b00000000000000000000000000000000 A
b10000000000000000000000000000000 B
#442
b00000000000000000000000000000000 A
b00000000000000000000000000000000 B
#444
b00000000000000000000000000000000 A
b00011001000001111111111111111111 B
#446
b00000000000000000000000000000000 A
b11001011001100001110011001010000 B
#448
b00000000000000000000000000000000 A
b10000000000000000000000000000000 B
#450
b00010000000000000000000000000000 A
b00000000000000000000000000000000 B
#452
b00010000000000000000000000000000 A
b00000000000000000000000000000000 B
#454
b01111011010111011111111111111111 A
b00000000000000000000000000000000 B
#456
b00000000000000000000000000000000 A
b11111110000000000000000000000000 B
#458
b00000000000000000000000000000000 A
b00000000000000000000000000000000 B
#460
b00000000000000000000000000000000 A
b11100110110110111111111111111111 B
#462
b00000000000000000000000000000000 A
b00010000000000000000000000000000 B
#464
b10000000000000000000000000000000 A
b11110100111101001000011000100000 B
#466
b10000000000000000000000000000000 A
b00010000000000000000000000000000 B
#468
b01101010111110111111111111111111 A
b00000000000000000000000000000000 B
#470
b00000000000000000000000000000000 A
b00000000000000000000000000000000 B
#472
b11110110100110100000101101001000 A
b00101011110010011111111111111111 B
#474
b00000000000000000000000000000000 A
b00010000000000000000000000000000 B
#476
b00010000000000000000000000000000 A
b01110100110110111111111111111111 B
#478
b00000000000000000000000000000000 A
b00000000000000000000000000000000 B
#480
b00010000000000000000000000000000 A
b00010000000000000000000000000000 B
#482
b11111010100010111111111111111111 A
b00000000000000000000000000000000 B
#484
b10000000000000000000000000000000 A
b00000000000000000000000000000000 B
#486
b01101000101101100011010100110000 A
b01101011001010111111111111111111 B
#488
b10000000000000000000000000000000 A
b10000000000000000000000000000000 B
#490
b00000000000000000000000000000000 A
b00010000000000000000000000000000 B
#492
b10000000000000000000000000000000 A
b00000000000000000000000000000000 B
#494
b00010000000000000000000000000000 A
b00000000000000000000000000000000 B
#496
b00000000000000000000000000000000 A
b00010000000000000000000000000000 B
#498
b10001011000110010011000000010000 A
b10000000000000000000000000000000 B
#500
b00010000000000000000000000000000 A
b00000000000000000000000000000000 B
#502
b10011110110101111111111111111111 A
b10000000000000000000000000000000 B
#504
b10000000000000000000000000000000 A
b00010000000000000000000000000000 B
#506
b00010000000000000000000000000000 A
b00010000000000000000000000000000 B
#508
b00000000000000000000000000000000 A
b00100001111010100000000001100000 B
#510
b00110101110000101010111111111111 A
b01100110010110111111111111111111 B
#512
b10110101000010011111111111111111 A
b00010000000000000000000000000000 B
#514
b00010000000000000000000000000000 A
b00101110011100101100101011101000 B
#516
b00000000000000000000000000000000 A
b01100110010110111111111111111111 B
#518
b00000000000000000000000000000000 A
b10011001111000000011111111111111 B
#520
b00000000000000000000000000000000 A
b00010000000000000000000000000000 B
#522
b00000000000000000000000000000000 A
b00110110010010011111111111111111 B
#524
b00000000000000000000000000000000 A
b00010000000000000000000000000000 B
#526
b00010000000000000000000000000000 A
b00000000000000000000000000000000 B
#528
b00000000000000000000000000000000 A
b00000000000000000000000000000000 B
#530
b00010000000000000000000000000000 A
b11000011111110011111111111111111 B
#532
b01000001110010001111011111010000 A
b00011101010010010011000000000000 B
#534
b01111010011010011111111111111111 A
b10000000000000000000000000000000 B
